ior_research/IORReceiver.py
ior_research/IORTransmitter.py
ior_research/IOTClient.py
ior_research/__init__.py
ior_research/argparser.py
ior_research/mqtt.py
ior_research/bean_definations/__init__.py
ior_research/bean_definations/bean.py
ior_research/bean_definations/mqtt/__init__.py
ior_research/events/__init__.py
ior_research/events/drone/__init__.py
ior_research/events/drone/conts.py
ior_research/utils/__init__.py
ior_research/utils/aes.py
ior_research/utils/httpclients.py
ior_research/utils/initializers.py
ior_research/utils/proxy.py
ior_research/utils/serialization.py
ior_research/utils/text.py
ior_research/utils/video.py
ior_research/utils/consts/__init__.py
ior_research/utils/consts/envs.py
ior_research/utils/filterchains/__init__.py
ior_research/utils/filterchains/ev3.py
ior_research/utils/filterchains/mqtt.py
ior_research/vechiles/__init__.py
ior_research/vechiles/ev3.py
ior_research-2.0.1.dist-info/LICENSE
ior_research-2.0.1.dist-info/LICENSE.txt
ior_research-2.0.1.dist-info/METADATA
ior_research-2.0.1.dist-info/WHEEL
ior_research-2.0.1.dist-info/top_level.txt
ior_research-2.0.1.dist-info/RECORD
