Metadata-Version: 2.1
Name: ior_research
Version: 2.0.1
Summary: A platform to control robots and electronic device over Internet
Home-page: https://github.com/mayank31313/ior-python
Author: Mayank Shinde
Author-email: mayank31313@gmail.com
Keywords: ior,iot,network_robos,control_net
Classifier: Programming Language :: Python :: 3
Classifier: Operating System :: OS Independent
Classifier: Intended Audience :: Developers
License-File: LICENSE
License-File: LICENSE.txt
